[
  {
    "avatar_id": "SYN-GK20",
    "position_group": "GK",
    "metric": "saves_p90",
    "mean": 2.8588238806,
    "arithmetic_mean": 2.9314043426,
    "median": 2.748773842,
    "std": 1.1016648494,
    "ci95_low": 2.4228560066,
    "ci95_high": 3.4018874051,
    "position_percentile": 61.9047619048,
    "direction": 1,
    "actual_n": 20
  },
  {
    "avatar_id": "SYN-GK20",
    "position_group": "GK",
    "metric": "goals_conceded_p90",
    "mean": 1.0590934091,
    "arithmetic_mean": 1.0762925844,
    "median": 1.0349182764,
    "std": 0.54587849,
    "ci95_low": 0.8162608557,
    "ci95_high": 1.3115898874,
    "position_percentile": 33.3333333333,
    "direction": -1,
    "actual_n": 20
  },
  {
    "avatar_id": "SYN-GK20",
    "position_group": "GK",
    "metric": "pass_accuracy",
    "mean": 72.6794904505,
    "arithmetic_mean": 72.4008184955,
    "median": 73.8288624921,
    "std": 8.2123354279,
    "ci95_low": 68.5348851539,
    "ci95_high": 76.1190547305,
    "position_percentile": 59.5238095238,
    "direction": 1,
    "actual_n": 20
  },
  {
    "avatar_id": "SYN-GK20",
    "position_group": "GK",
    "metric": "passes_p90",
    "mean": 29.9247544599,
    "arithmetic_mean": 30.6531823145,
    "median": 30.1904761905,
    "std": 7.1940571821,
    "ci95_low": 27.6915858425,
    "ci95_high": 32.7766329856,
    "position_percentile": 66.6666666667,
    "direction": 1,
    "actual_n": 20
  },
  {
    "avatar_id": "SYN-CB20",
    "position_group": "CB",
    "metric": "interceptions_p90",
    "mean": 1.1980837113,
    "arithmetic_mean": 1.2132825802,
    "median": 1.0819051055,
    "std": 0.4250444647,
    "ci95_low": 0.9975321937,
    "ci95_high": 1.4264935683,
    "position_percentile": 72.6315789474,
    "direction": 1,
    "actual_n": 20
  },
  {
    "avatar_id": "SYN-CB20",
    "position_group": "CB",
    "metric": "tackles_p90",
    "mean": 1.7595269672,
    "arithmetic_mean": 1.8248172806,
    "median": 1.641025641,
    "std": 0.9922662719,
    "ci95_low": 1.3084424078,
    "ci95_high": 2.2456593661,
    "position_percentile": 78.9473684211,
    "direction": 1,
    "actual_n": 20
  },
  {
    "avatar_id": "SYN-CB20",
    "position_group": "CB",
    "metric": "blocks_p90",
    "mean": 0.5724502311,
    "arithmetic_mean": 0.6079601849,
    "median": 0.55,
    "std": 0.4349037728,
    "ci95_low": 0.4020748702,
    "ci95_high": 0.7587323823,
    "position_percentile": 53.6842105263,
    "direction": 1,
    "actual_n": 20
  },
  {
    "avatar_id": "SYN-CB20",
    "position_group": "CB",
    "metric": "duel_win_rate",
    "mean": 0.6733408705,
    "arithmetic_mean": 0.6705148017,
    "median": 0.6939799331,
    "std": 0.0745376456,
    "ci95_low": 0.6362805857,
    "ci95_high": 0.7060934428,
    "position_percentile": 73.6842105263,
    "direction": 1,
    "actual_n": 20
  },
  {
    "avatar_id": "SYN-CB20",
    "position_group": "CB",
    "metric": "pass_accuracy",
    "mean": 92.5188474964,
    "arithmetic_mean": 92.1832462668,
    "median": 92.5186104218,
    "std": 3.0329336321,
    "ci95_low": 91.050856725,
    "ci95_high": 93.6951732226,
    "position_percentile": 72.6315789474,
    "direction": 1,
    "actual_n": 20
  },
  {
    "avatar_id": "SYN-CB20",
    "position_group": "CB",
    "metric": "passes_p90",
    "mean": 68.1097635657,
    "arithmetic_mean": 68.7735251383,
    "median": 66.4074889868,
    "std": 15.9766618319,
    "ci95_low": 60.7805963543,
    "ci95_high": 76.1350136877,
    "position_percentile": 75.7894736842,
    "direction": 1,
    "actual_n": 20
  },
  {
    "avatar_id": "SYN-CB20",
    "position_group": "CB",
    "metric": "cards_p90",
    "mean": 0.0260224122,
    "arithmetic_mean": 0.0561567956,
    "median": 0.0,
    "std": 0.1208903349,
    "ci95_low": 0.0,
    "ci95_high": 0.0935579537,
    "position_percentile": 62.1052631579,
    "direction": -1,
    "actual_n": 20
  },
  {
    "avatar_id": "SYN-FB20",
    "position_group": "FB",
    "metric": "interceptions_p90",
    "mean": 1.1594149564,
    "arithmetic_mean": 1.2124600695,
    "median": 1.2555588689,
    "std": 0.6301200836,
    "ci95_low": 0.9081411483,
    "ci95_high": 1.483408573,
    "position_percentile": 67.5,
    "direction": 1,
    "actual_n": 20
  },
  {
    "avatar_id": "SYN-FB20",
    "position_group": "FB",
    "metric": "tackles_p90",
    "mean": 2.6964239046,
    "arithmetic_mean": 2.7618786854,
    "median": 2.5441496699,
    "std": 0.9859869117,
    "ci95_low": 2.2996448974,
    "ci95_high": 3.1734890175,
    "position_percentile": 72.5,
    "direction": 1,
    "actual_n": 20
  },
  {
    "avatar_id": "SYN-FB20",
    "position_group": "FB",
    "metric": "duel_win_rate",
    "mean": 0.6160568689,
    "arithmetic_mean": 0.6124614826,
    "median": 0.6123737374,
    "std": 0.0779253405,
    "ci95_low": 0.5777753745,
    "ci95_high": 0.6474476121,
    "position_percentile": 75.0,
    "direction": 1,
    "actual_n": 20
  },
  {
    "avatar_id": "SYN-FB20",
    "position_group": "FB",
    "metric": "key_passes_p90",
    "mean": 1.1601623347,
    "arithmetic_mean": 1.1924300477,
    "median": 1.0900791236,
    "std": 0.7117447303,
    "ci95_low": 0.8332521493,
    "ci95_high": 1.4976313361,
    "position_percentile": 73.75,
    "direction": 1,
    "actual_n": 20
  },
  {
    "avatar_id": "SYN-FB20",
    "position_group": "FB",
    "metric": "assists_p90",
    "mean": 0.1243909355,
    "arithmetic_mean": 0.1483245613,
    "median": 0.0,
    "std": 0.1803258036,
    "ci95_low": 0.0440027394,
    "ci95_high": 0.2208549236,
    "position_percentile": 72.5,
    "direction": 1,
    "actual_n": 20
  },
  {
    "avatar_id": "SYN-FB20",
    "position_group": "FB",
    "metric": "dribbles_completed_p90",
    "mean": 0.9093977044,
    "arithmetic_mean": 0.96271639,
    "median": 0.6719014655,
    "std": 0.7678516251,
    "ci95_low": 0.5860030237,
    "ci95_high": 1.2720558778,
    "position_percentile": 73.75,
    "direction": 1,
    "actual_n": 20
  },
  {
    "avatar_id": "SYN-FB20",
    "position_group": "FB",
    "metric": "pass_accuracy",
    "mean": 87.0741272828,
    "arithmetic_mean": 85.8803095486,
    "median": 87.6708018698,
    "std": 7.1712153377,
    "ci95_low": 83.2529404609,
    "ci95_high": 89.3166017654,
    "position_percentile": 58.75,
    "direction": 1,
    "actual_n": 20
  },
  {
    "avatar_id": "SYN-DM20",
    "position_group": "DM",
    "metric": "interceptions_p90",
    "mean": 1.0993259908,
    "arithmetic_mean": 1.1402491803,
    "median": 1.1309312357,
    "std": 0.646809161,
    "ci95_low": 0.8285778696,
    "ci95_high": 1.4165059901,
    "position_percentile": 59.375,
    "direction": 1,
    "actual_n": 20
  },
  {
    "avatar_id": "SYN-DM20",
    "position_group": "DM",
    "metric": "tackles_p90",
    "mean": 2.2880148002,
    "arithmetic_mean": 2.3264841362,
    "median": 2.3007108304,
    "std": 1.0353082484,
    "ci95_low": 1.8397586901,
    "ci95_high": 2.7871982119,
    "position_percentile": 62.5,
    "direction": 1,
    "actual_n": 20
  },
  {
    "avatar_id": "SYN-DM20",
    "position_group": "DM",
    "metric": "duel_win_rate",
    "mean": 0.5749649434,
    "arithmetic_mean": 0.5678632685,
    "median": 0.5643939394,
    "std": 0.1318865398,
    "ci95_low": 0.5091507263,
    "ci95_high": 0.6338185761,
    "position_percentile": 56.25,
    "direction": 1,
    "actual_n": 20
  },
  {
    "avatar_id": "SYN-DM20",
    "position_group": "DM",
    "metric": "passes_p90",
    "mean": 67.9580441194,
    "arithmetic_mean": 69.9338377078,
    "median": 66.6370967742,
    "std": 20.34010103,
    "ci95_low": 59.3733519171,
    "ci95_high": 78.2576591323,
    "position_percentile": 68.75,
    "direction": 1,
    "actual_n": 20
  },
  {
    "avatar_id": "SYN-DM20",
    "position_group": "DM",
    "metric": "pass_accuracy",
    "mean": 91.0864520932,
    "arithmetic_mean": 90.9756297207,
    "median": 91.5343652018,
    "std": 3.231831912,
    "ci95_low": 89.5064443745,
    "ci95_high": 92.5444554077,
    "position_percentile": 56.25,
    "direction": 1,
    "actual_n": 20
  },
  {
    "avatar_id": "SYN-DM20",
    "position_group": "DM",
    "metric": "key_passes_p90",
    "mean": 0.8905992388,
    "arithmetic_mean": 1.0294813825,
    "median": 0.933544729,
    "std": 0.7789895396,
    "ci95_low": 0.6642387824,
    "ci95_high": 1.2535048944,
    "position_percentile": 46.875,
    "direction": 1,
    "actual_n": 20
  },
  {
    "avatar_id": "SYN-DM20",
    "position_group": "DM",
    "metric": "cards_p90",
    "mean": 0.0203925288,
    "arithmetic_mean": 0.0401205557,
    "median": 0.0,
    "std": 0.0844078738,
    "ci95_low": 0.0,
    "ci95_high": 0.0667166454,
    "position_percentile": 62.5,
    "direction": -1,
    "actual_n": 20
  },
  {
    "avatar_id": "SYN-CM20",
    "position_group": "CM",
    "metric": "passes_p90",
    "mean": 55.8764010857,
    "arithmetic_mean": 55.5417731937,
    "median": 61.8386996904,
    "std": 14.9665305477,
    "ci95_low": 49.0205565978,
    "ci95_high": 63.0035832219,
    "position_percentile": 79.6875,
    "direction": 1,
    "actual_n": 20
  },
  {
    "avatar_id": "SYN-CM20",
    "position_group": "CM",
    "metric": "pass_accuracy",
    "mean": 88.7340144763,
    "arithmetic_mean": 88.521519897,
    "median": 89.2033229739,
    "std": 4.5127870261,
    "ci95_low": 86.7335539956,
    "ci95_high": 90.6432684569,
    "position_percentile": 76.5625,
    "direction": 1,
    "actual_n": 20
  },
  {
    "avatar_id": "SYN-CM20",
    "position_group": "CM",
    "metric": "key_passes_p90",
    "mean": 1.4474473224,
    "arithmetic_mean": 1.5332939889,
    "median": 1.3329685363,
    "std": 0.8975050144,
    "ci95_low": 1.061804731,
    "ci95_high": 1.921544687,
    "position_percentile": 81.25,
    "direction": 1,
    "actual_n": 20
  },
  {
    "avatar_id": "SYN-CM20",
    "position_group": "CM",
    "metric": "assists_p90",
    "mean": 0.1820092205,
    "arithmetic_mean": 0.2380173531,
    "median": 0.0,
    "std": 0.3236785842,
    "ci95_low": 0.0645835425,
    "ci95_high": 0.346648462,
    "position_percentile": 75.0,
    "direction": 1,
    "actual_n": 20
  },
  {
    "avatar_id": "SYN-CM20",
    "position_group": "CM",
    "metric": "dribbles_completed_p90",
    "mean": 0.8248872299,
    "arithmetic_mean": 0.8929285299,
    "median": 0.6737469566,
    "std": 0.6525996248,
    "ci95_low": 0.5598513956,
    "ci95_high": 1.1546275921,
    "position_percentile": 59.375,
    "direction": 1,
    "actual_n": 20
  },
  {
    "avatar_id": "SYN-CM20",
    "position_group": "CM",
    "metric": "tackles_p90",
    "mean": 2.2784739017,
    "arithmetic_mean": 2.3244568164,
    "median": 2.2402077776,
    "std": 0.8652067795,
    "ci95_low": 1.8774749818,
    "ci95_high": 2.707651396,
    "position_percentile": 62.5,
    "direction": 1,
    "actual_n": 20
  },
  {
    "avatar_id": "SYN-CM20",
    "position_group": "CM",
    "metric": "interceptions_p90",
    "mean": 1.2285877009,
    "arithmetic_mean": 1.2108028592,
    "median": 1.4047087477,
    "std": 0.6709550375,
    "ci95_low": 0.9028352933,
    "ci95_high": 1.567796872,
    "position_percentile": 59.375,
    "direction": 1,
    "actual_n": 20
  },
  {
    "avatar_id": "SYN-AM20",
    "position_group": "AM",
    "metric": "goals_p90",
    "mean": 0.1277442913,
    "arithmetic_mean": 0.1853501554,
    "median": 0.0,
    "std": 0.3629266344,
    "ci95_low": 0.0200534759,
    "ci95_high": 0.3196123987,
    "position_percentile": 68.4210526316,
    "direction": 1,
    "actual_n": 19
  },
  {
    "avatar_id": "SYN-AM20",
    "position_group": "AM",
    "metric": "assists_p90",
    "mean": 0.1331199931,
    "arithmetic_mean": 0.1664757833,
    "median": 0.0,
    "std": 0.2795397983,
    "ci95_low": 0.0355154198,
    "ci95_high": 0.2818898522,
    "position_percentile": 63.1578947368,
    "direction": 1,
    "actual_n": 19
  },
  {
    "avatar_id": "SYN-AM20",
    "position_group": "AM",
    "metric": "shots_p90",
    "mean": 1.252755104,
    "arithmetic_mean": 1.2800048728,
    "median": 1.08,
    "std": 0.7470456346,
    "ci95_low": 0.9315767332,
    "ci95_high": 1.6115051382,
    "position_percentile": 57.8947368421,
    "direction": 1,
    "actual_n": 19
  },
  {
    "avatar_id": "SYN-AM20",
    "position_group": "AM",
    "metric": "shots_on_target_rate",
    "mean": 0.3533539989,
    "arithmetic_mean": 0.3556325254,
    "median": 0.3846153846,
    "std": 0.2911028967,
    "ci95_low": 0.2154077295,
    "ci95_high": 0.4959470554,
    "position_percentile": 42.1052631579,
    "direction": 1,
    "actual_n": 19
  },
  {
    "avatar_id": "SYN-AM20",
    "position_group": "AM",
    "metric": "key_passes_p90",
    "mean": 1.2463792857,
    "arithmetic_mean": 1.237580487,
    "median": 1.25,
    "std": 0.6840883439,
    "ci95_low": 0.915753235,
    "ci95_high": 1.5484409017,
    "position_percentile": 47.3684210526,
    "direction": 1,
    "actual_n": 19
  },
  {
    "avatar_id": "SYN-AM20",
    "position_group": "AM",
    "metric": "dribbles_completed_p90",
    "mean": 1.2473599375,
    "arithmetic_mean": 1.291497488,
    "median": 1.1538461538,
    "std": 0.9461232518,
    "ci95_low": 0.8319428958,
    "ci95_high": 1.7131586216,
    "position_percentile": 52.6315789474,
    "direction": 1,
    "actual_n": 19
  },
  {
    "avatar_id": "SYN-AM20",
    "position_group": "AM",
    "metric": "pass_accuracy",
    "mean": 84.7048478249,
    "arithmetic_mean": 84.8809783225,
    "median": 84.5303867403,
    "std": 4.8300480585,
    "ci95_low": 82.464313219,
    "ci95_high": 87.0117580894,
    "position_percentile": 52.6315789474,
    "direction": 1,
    "actual_n": 19
  },
  {
    "avatar_id": "SYN-W20",
    "position_group": "W",
    "metric": "goals_p90",
    "mean": 0.3939471529,
    "arithmetic_mean": 0.4075490266,
    "median": 0.3998711038,
    "std": 0.3546398553,
    "ci95_low": 0.2150660987,
    "ci95_high": 0.586420231,
    "position_percentile": 72.0,
    "direction": 1,
    "actual_n": 20
  },
  {
    "avatar_id": "SYN-W20",
    "position_group": "W",
    "metric": "assists_p90",
    "mean": 0.3476957565,
    "arithmetic_mean": 0.3825032635,
    "median": 0.3114186851,
    "std": 0.3050189594,
    "ci95_low": 0.2300114868,
    "ci95_high": 0.5118283896,
    "position_percentile": 78.0,
    "direction": 1,
    "actual_n": 20
  },
  {
    "avatar_id": "SYN-W20",
    "position_group": "W",
    "metric": "shots_on_target_rate",
    "mean": 0.6468770813,
    "arithmetic_mean": 0.617501665,
    "median": 0.6076923077,
    "std": 0.2694607657,
    "ci95_low": 0.5080100368,
    "ci95_high": 0.7416701267,
    "position_percentile": 68.0,
    "direction": 1,
    "actual_n": 20
  },
  {
    "avatar_id": "SYN-W20",
    "position_group": "W",
    "metric": "key_passes_p90",
    "mean": 2.3643232765,
    "arithmetic_mean": 2.328957498,
    "median": 2.3913043478,
    "std": 0.7998877073,
    "ci95_low": 2.0003987736,
    "ci95_high": 2.7124173386,
    "position_percentile": 78.0,
    "direction": 1,
    "actual_n": 20
  },
  {
    "avatar_id": "SYN-W20",
    "position_group": "W",
    "metric": "dribbles_completed_p90",
    "mean": 1.7749629419,
    "arithmetic_mean": 1.8538692354,
    "median": 1.660899654,
    "std": 0.8454822633,
    "ci95_low": 1.431929604,
    "ci95_high": 2.1873951806,
    "position_percentile": 70.0,
    "direction": 1,
    "actual_n": 20
  },
  {
    "avatar_id": "SYN-W20",
    "position_group": "W",
    "metric": "dribble_success_rate",
    "mean": 0.5172055985,
    "arithmetic_mean": 0.5332391164,
    "median": 0.5,
    "std": 0.143650135,
    "ci95_low": 0.4648982304,
    "ci95_high": 0.5889966563,
    "position_percentile": 74.0,
    "direction": 1,
    "actual_n": 20
  },
  {
    "avatar_id": "SYN-W20",
    "position_group": "W",
    "metric": "duel_win_rate",
    "mean": 0.5068871307,
    "arithmetic_mean": 0.5076566668,
    "median": 0.5051020408,
    "std": 0.0596714233,
    "ci95_low": 0.4773765821,
    "ci95_high": 0.5378880409,
    "position_percentile": 76.0,
    "direction": 1,
    "actual_n": 20
  },
  {
    "avatar_id": "SYN-ST20",
    "position_group": "ST",
    "metric": "goals_p90",
    "mean": 0.7600427581,
    "arithmetic_mean": 0.7466145752,
    "median": 0.8182494421,
    "std": 0.369787102,
    "ci95_low": 0.575590291,
    "ci95_high": 0.9267466676,
    "position_percentile": 71.4285714286,
    "direction": 1,
    "actual_n": 20
  },
  {
    "avatar_id": "SYN-ST20",
    "position_group": "ST",
    "metric": "assists_p90",
    "mean": 0.2069076095,
    "arithmetic_mean": 0.2195583457,
    "median": 0.2103516817,
    "std": 0.2099063806,
    "ci95_low": 0.1051874499,
    "ci95_high": 0.31997402,
    "position_percentile": 69.387755102,
    "direction": 1,
    "actual_n": 20
  },
  {
    "avatar_id": "SYN-ST20",
    "position_group": "ST",
    "metric": "shots_p90",
    "mean": 2.3820136533,
    "arithmetic_mean": 2.4099459702,
    "median": 2.3960883802,
    "std": 1.1188513785,
    "ci95_low": 1.8799243378,
    "ci95_high": 2.9462315503,
    "position_percentile": 73.4693877551,
    "direction": 1,
    "actual_n": 20
  },
  {
    "avatar_id": "SYN-ST20",
    "position_group": "ST",
    "metric": "shots_on_target_rate",
    "mean": 0.651897653,
    "arithmetic_mean": 0.6529466938,
    "median": 0.6547619048,
    "std": 0.2025352258,
    "ci95_low": 0.5641321699,
    "ci95_high": 0.7423985323,
    "position_percentile": 59.1836734694,
    "direction": 1,
    "actual_n": 20
  },
  {
    "avatar_id": "SYN-ST20",
    "position_group": "ST",
    "metric": "key_passes_p90",
    "mean": 1.2159468412,
    "arithmetic_mean": 1.2900922846,
    "median": 1.1833237327,
    "std": 0.8921977526,
    "ci95_low": 0.8815525991,
    "ci95_high": 1.6242532856,
    "position_percentile": 73.4693877551,
    "direction": 1,
    "actual_n": 20
  },
  {
    "avatar_id": "SYN-ST20",
    "position_group": "ST",
    "metric": "duel_win_rate",
    "mean": 0.4494223628,
    "arithmetic_mean": 0.4483546332,
    "median": 0.4562423501,
    "std": 0.0908835343,
    "ci95_low": 0.4095056282,
    "ci95_high": 0.4893026634,
    "position_percentile": 61.2244897959,
    "direction": 1,
    "actual_n": 20
  },
  {
    "avatar_id": "SYN-ST20",
    "position_group": "ST",
    "metric": "fouls_drawn_p90",
    "mean": 1.3392361297,
    "arithmetic_mean": 1.3752592487,
    "median": 1.2113713182,
    "std": 0.7716773453,
    "ci95_low": 1.0034028232,
    "ci95_high": 1.6973041221,
    "position_percentile": 61.2244897959,
    "direction": 1,
    "actual_n": 20
  }
]