{
  "status": "complete_lineup_position_evidence_audited",
  "generated_at_utc": "2026-07-20T15:41:53.890713+00:00",
  "network_calls": 0,
  "fixture_team_lineup_groups": 13193,
  "structurally_complete_groups": 3149,
  "complete_group_rate": 0.23868718259683167,
  "complete_role_observations": 33710,
  "players_with_complete_role_evidence": 5169,
  "eligible_900_minutes_and_3_observations_by_role": {
    "GK": 34,
    "RB": 33,
    "RCB": 38,
    "LCB": 36,
    "LB": 33,
    "DM": 53,
    "CM": 44,
    "AM": 23,
    "RW": 27,
    "LW": 32,
    "ST": 46
  },
  "all_roles_have_20_candidates": true,
  "priority_candidate_fixture_team_pairs": 21538,
  "high_impact_priority_pairs": 3698,
  "high_impact_players_needing_more_complete_lineups": 220,
  "classification_policy": "only exact 11-player grids whose row sizes match a supported declared formation",
  "next_action": "extract or recover complete startXI lineups for the priority fixture-team list"
}